echovault/__init__.py
echovault/__init__.py~
echovault/_container.py
echovault/_container.py~
echovault/db.py~
echovault/dict.py
echovault/dict.py~
echovault/list.py
echovault/list.py~
echovault/table.py~
echovault/vault.py
echovault/vault.py.bck
echovault/vault.py~
echovault-0.2.8.dist-info/METADATA
echovault-0.2.8.dist-info/WHEEL
echovault-0.2.8.dist-info/RECORD
