Metadata-Version: 2.1
Name: echovault
Version: 0.2.8
Summary: echovault is git data storage
Author: Charles Bajeux
Author-email: charles.bajeux@gmail.com
Requires-Python: >=3.11,<4.0
Classifier: Programming Language :: Python :: 3
Classifier: Programming Language :: Python :: 3.11
Classifier: Programming Language :: Python :: 3.12
Requires-Dist: dulwich (>=0.21.7,<0.22.0)
